turtle_tetris/__init__.py
turtle_tetris/tetris.py
turtle_tetris-1.0.dist-info/LICENSE
turtle_tetris-1.0.dist-info/METADATA
turtle_tetris-1.0.dist-info/WHEEL
turtle_tetris-1.0.dist-info/top_level.txt
turtle_tetris-1.0.dist-info/RECORD
